remla12_lib_release/__init__.py
remla12_lib_release/version_util.py
remla12_lib_release-0.1.9.dist-info/METADATA
remla12_lib_release-0.1.9.dist-info/WHEEL
remla12_lib_release-0.1.9.dist-info/top_level.txt
remla12_lib_release-0.1.9.dist-info/RECORD
