Metadata-Version: 2.1
Name: remla12-lib-release
Version: 0.1.9
Summary: A version-aware library for REMLA12 project
Home-page: https://github.com/remla23-team12/lib
Requires-Python: >=3.6
